{"schemaVersion": "2.0", "monologues": [{"speaker": {"id": "medecin", "name": ""}, "start": 1.7599999999999998, "end": 2.74, "terms": [{"start": 1.7599999999999998, "end": 2.74, "text": "allo", "type": "WORD"}, {"start": 2.74, "end": 2.74, "text": "?", "type": "PUNCTUATION"}]}, {"speaker": {"id": "patient", "name": ""}, "start": 3.33, "end": 4.109999999999999, "terms": [{"start": 3.33, "end": 3.7200000000000006, "text": "oui", "type": "WORD"}, {"start": 3.7200000000000006, "end": 4.109999999999999, "text": "allo", "type": "WORD"}, {"start": 4.109999999999999, "end": 4.109999999999999, "text": "?", "type": "PUNCTUATION"}]}, {"speaker": {"id": "medecin", "name": ""}, "start": 4.119999999999999, "end": 7.460000000000001, "terms": [{"start": 4.119999999999999, "end": 4.949999999999999, "text": "oui", "type": "WORD"}, {"start": 4.949999999999999, "end": 5.789999999999999, "text": "bonjour", "type": "WORD"}, {"start": 5.789999999999999, "end": 6.619999999999999, "text": "docteur", "type": "WORD"}, {"start": 6.619999999999999, "end": 6.699999999999999, "text": "RICHARDO", "type": "WORD"}, {"start": 6.699999999999999, "end": 6.789999999999999, "text": "vous", "type": "WORD"}, {"start": 6.789999999999999, "end": 6.869999999999999, "text": "appelez", "type": "WORD"}, {"start": 6.869999999999999, "end": 6.960000000000001, "text": "parce", "type": "WORD"}, {"start": 6.960000000000001, "end": 7.039999999999999, "text": "que", "type": "WORD"}, {"start": 7.039999999999999, "end": 7.119999999999999, "text": "vous", "type": "WORD"}, {"start": 7.119999999999999, "end": 7.210000000000001, "text": "avez", "type": "WORD"}, {"start": 7.210000000000001, "end": 7.289999999999999, "text": "mal", "type": "WORD"}, {"start": 7.289999999999999, "end": 7.380000000000001, "text": "au", "type": "WORD"}, {"start": 7.380000000000001, "end": 7.460000000000001, "text": "ventre", "type": "WORD"}, {"start": 7.460000000000001, "end": 7.460000000000001, "text": "?", "type": "PUNCTUATION"}]}, {"speaker": {"id": "patient", "name": ""}, "start": 8.57, "end": 9.24, "terms": [{"start": 8.57, "end": 9.24, "text": "oui", "type": "WORD"}]}, {"speaker": {"id": "medecin", "name": ""}, "start": 9.24, "end": 11.149999999999999, "terms": [{"start": 9.24, "end": 9.88, "text": "alors", "type": "WORD"}, {"start": 9.88, "end": 10.51, "text": "vous", "type": "WORD"}, {"start": 10.51, "end": 10.59, "text": "avez", "type": "WORD"}, {"start": 10.59, "end": 10.67, "text": "mal", "type": "WORD"}, {"start": 10.67, "end": 10.75, "text": "au", "type": "WORD"}, {"start": 10.75, "end": 10.829999999999998, "text": "ventre", "type": "WORD"}, {"start": 10.829999999999998, "end": 10.91, "text": "depuis", "type": "WORD"}, {"start": 10.91, "end": 10.989999999999998, "text": "combien", "type": "WORD"}, {"start": 10.989999999999998, "end": 11.07, "text": "de", "type": "WORD"}, {"start": 11.07, "end": 11.149999999999999, "text": "temps", "type": "WORD"}, {"start": 11.149999999999999, "end": 11.149999999999999, "text": "?", "type": "PUNCTUATION"}]}, {"speaker": {"id": "patient", "name": ""}, "start": 12.190000000000001, "end": 13.91, "terms": [{"start": 12.190000000000001, "end": 12.620000000000001, "text": "hum", "type": "WORD"}, {"start": 12.620000000000001, "end": 13.05, "text": "depuis", "type": "WORD"}, {"start": 13.05, "end": 13.48, "text": "ce", "type": "WORD"}, {"start": 13.48, "end": 13.91, "text": "matin", "type": "WORD"}]}, {"speaker": {"id": "medecin", "name": ""}, "start": 13.96, "end": 16.93, "terms": [{"start": 13.96, "end": 14.27, "text": "depuis", "type": "WORD"}, {"start": 14.27, "end": 14.57, "text": "ce", "type": "WORD"}, {"start": 14.57, "end": 14.829999999999998, "text": "matin", "type": "WORD"}, {"start": 14.829999999999998, "end": 14.829999999999998, "text": ".", "type": "PUNCTUATION"}, {"start": 14.829999999999998, "end": 15.09, "text": "est", "type": "WORD"}, {"start": 15.09, "end": 15.36, "text": "ce", "type": "WORD"}, {"start": 15.36, "end": 15.620000000000001, "text": "qu'il", "type": "WORD"}, {"start": 15.620000000000001, "end": 15.879999999999999, "text": "y", "type": "WORD"}, {"start": 15.879999999999999, "end": 16.14, "text": "a", "type": "WORD"}, {"start": 16.14, "end": 16.4, "text": "eu", "type": "WORD"}, {"start": 16.4, "end": 16.67, "text": "des", "type": "WORD"}, {"start": 16.67, "end": 16.93, "text": "vomissements", "type": "WORD"}, {"start": 16.93, "end": 16.93, "text": "?", "type": "PUNCTUATION"}]}, {"speaker": {"id": "patient", "name": ""}, "start": 18.27, "end": 18.66, "terms": [{"start": 18.27, "end": 18.66, "text": "non", "type": "WORD"}]}, {"speaker": {"id": "medecin", "name": ""}, "start": 19.1, "end": 21.09, "terms": [{"start": 19.1, "end": 19.29, "text": "pas", "type": "WORD"}, {"start": 19.29, "end": 19.47, "text": "de", "type": "WORD"}, {"start": 19.47, "end": 19.65, "text": "vomissements", "type": "WORD"}, {"start": 19.65, "end": 19.65, "text": ".", "type": "PUNCTUATION"}, {"start": 19.65, "end": 19.83, "text": "est", "type": "WORD"}, {"start": 19.83, "end": 20.01, "text": "ce", "type": "WORD"}, {"start": 20.01, "end": 20.19, "text": "qu'il", "type": "WORD"}, {"start": 20.19, "end": 20.37, "text": "y", "type": "WORD"}, {"start": 20.37, "end": 20.55, "text": "a", "type": "WORD"}, {"start": 20.55, "end": 20.73, "text": "eu", "type": "WORD"}, {"start": 20.73, "end": 20.91, "text": "des", "type": "WORD"}, {"start": 20.91, "end": 21.09, "text": "diarrhées", "type": "WORD"}, {"start": 21.09, "end": 21.09, "text": "?", "type": "PUNCTUATION"}]}, {"speaker": {"id": "patient", "name": ""}, "start": 22.49, "end": 22.88, "terms": [{"start": 22.49, "end": 22.88, "text": "non", "type": "WORD"}]}, {"speaker": {"id": "medecin", "name": ""}, "start": 23.07, "end": 25.83, "terms": [{"start": 23.07, "end": 23.26, "text": "pas", "type": "WORD"}, {"start": 23.26, "end": 23.44, "text": "de", "type": "WORD"}, {"start": 23.44, "end": 23.46, "text": "diarrhée", "type": "WORD"}, {"start": 23.46, "end": 23.46, "text": ".", "type": "PUNCTUATION"}, {"start": 23.46, "end": 23.48, "text": "est", "type": "WORD"}, {"start": 23.48, "end": 23.5, "text": "ce", "type": "WORD"}, {"start": 23.5, "end": 23.52, "text": "que", "type": "WORD"}, {"start": 23.52, "end": 23.53, "text": "vous", "type": "WORD"}, {"start": 23.53, "end": 23.55, "text": "avez", "type": "WORD"}, {"start": 23.55, "end": 23.57, "text": "des", "type": "WORD"}, {"start": 23.57, "end": 23.59, "text": "problèmes", "type": "WORD"}, {"start": 23.59, "end": 23.61, "text": "de", "type": "WORD"}, {"start": 23.61, "end": 25.83, "text": "santé", "type": "WORD"}, {"start": 25.83, "end": 25.83, "text": "?", "type": "PUNCTUATION"}]}, {"speaker": {"id": "patient", "name": ""}, "start": 27.54, "end": 31.0, "terms": [{"start": 27.54, "end": 28.11, "text": "hum", "type": "WORD"}, {"start": 28.11, "end": 28.689999999999998, "text": "j'ai", "type": "WORD"}, {"start": 28.689999999999998, "end": 29.270000000000003, "text": "un", "type": "WORD"}, {"start": 29.270000000000003, "end": 29.840000000000003, "text": "peu", "type": "WORD"}, {"start": 29.840000000000003, "end": 30.42, "text": "de", "type": "WORD"}, {"start": 30.42, "end": 31.0, "text": "diabète", "type": "WORD"}]}, {"speaker": {"id": "medecin", "name": ""}, "start": 31.450000000000003, "end": 33.15, "terms": [{"start": 31.450000000000003, "end": 31.79, "text": "diabète", "type": "WORD"}, {"start": 31.79, "end": 31.79, "text": ".", "type": "PUNCTUATION"}, {"start": 31.79, "end": 32.13, "text": "vous", "type": "WORD"}, {"start": 32.13, "end": 32.47, "text": "prenez", "type": "WORD"}, {"start": 32.47, "end": 32.81, "text": "de", "type": "WORD"}, {"start": 32.81, "end": 33.15, "text": "l'insuline", "type": "WORD"}, {"start": 33.15, "end": 33.15, "text": "?", "type": "PUNCTUATION"}]}, {"speaker": {"id": "patient", "name": ""}, "start": 34.58, "end": 35.1, "terms": [{"start": 34.58, "end": 34.84, "text": "hum", "type": "WORD"}, {"start": 34.84, "end": 35.1, "text": "oui", "type": "WORD"}]}, {"speaker": {"id": "medecin", "name": ""}, "start": 36.54, "end": 37.96, "terms": [{"start": 36.54, "end": 36.7, "text": "est", "type": "WORD"}, {"start": 36.7, "end": 36.86, "text": "ce", "type": "WORD"}, {"start": 36.86, "end": 37.02, "text": "que", "type": "WORD"}, {"start": 37.02, "end": 37.17, "text": "vous", "type": "WORD"}, {"start": 37.17, "end": 37.33, "text": "avez", "type": "WORD"}, {"start": 37.33, "end": 37.49, "text": "d'autres", "type": "WORD"}, {"start": 37.49, "end": 37.65, "text": "problèmes", "type": "WORD"}, {"start": 37.65, "end": 37.81, "text": "de", "type": "WORD"}, {"start": 37.81, "end": 37.96, "text": "santé", "type": "WORD"}, {"start": 37.96, "end": 37.96, "text": "?", "type": "PUNCTUATION"}]}, {"speaker": {"id": "patient", "name": ""}, "start": 40.35, "end": 41.06, "terms": [{"start": 40.35, "end": 41.06, "text": "non", "type": "WORD"}]}, {"speaker": {"id": "medecin", "name": ""}, "start": 41.27, "end": 43.93, "terms": [{"start": 41.27, "end": 41.56, "text": "non", "type": "WORD"}, {"start": 41.56, "end": 41.56, "text": ".", "type": "PUNCTUATION"}, {"start": 41.56, "end": 41.86, "text": "vous", "type": "WORD"}, {"start": 41.86, "end": 42.16, "text": "prenez", "type": "WORD"}, {"start": 42.16, "end": 42.45, "text": "pas", "type": "WORD"}, {"start": 42.45, "end": 42.75, "text": "d'autre", "type": "WORD"}, {"start": 42.75, "end": 43.05, "text": "médicament", "type": "WORD"}, {"start": 43.05, "end": 43.34, "text": "que", "type": "WORD"}, {"start": 43.34, "end": 43.64, "text": "de", "type": "WORD"}, {"start": 43.64, "end": 43.93, "text": "l'insuline", "type": "WORD"}, {"start": 43.93, "end": 43.93, "text": "?", "type": "PUNCTUATION"}]}, {"speaker": {"id": "patient", "name": ""}, "start": 45.45, "end": 46.81, "terms": [{"start": 45.45, "end": 46.13, "text": "hum", "type": "WORD"}, {"start": 46.13, "end": 46.81, "text": "non", "type": "WORD"}]}, {"speaker": {"id": "medecin", "name": ""}, "start": 49.2, "end": 56.01, "terms": [{"start": 49.2, "end": 50.9, "text": "alors", "type": "WORD"}, {"start": 50.9, "end": 52.61, "text": "là", "type": "WORD"}, {"start": 52.61, "end": 54.31, "text": "vous", "type": "WORD"}, {"start": 54.31, "end": 54.59, "text": "avez", "type": "WORD"}, {"start": 54.59, "end": 54.88, "text": "mal", "type": "WORD"}, {"start": 54.88, "end": 55.16, "text": "donc", "type": "WORD"}, {"start": 55.16, "end": 55.44, "text": "depuis", "type": "WORD"}, {"start": 55.44, "end": 55.73, "text": "ce", "type": "WORD"}, {"start": 55.73, "end": 55.79, "text": "matin", "type": "WORD"}, {"start": 55.79, "end": 55.84, "text": "vous", "type": "WORD"}, {"start": 55.84, "end": 55.9, "text": "avez", "type": "WORD"}, {"start": 55.9, "end": 55.95, "text": "pas", "type": "WORD"}, {"start": 55.95, "end": 55.96, "text": "vomi", "type": "WORD"}, {"start": 55.96, "end": 55.97, "text": "vous", "type": "WORD"}, {"start": 55.97, "end": 55.98, "text": "avez", "type": "WORD"}, {"start": 55.98, "end": 55.99, "text": "pas", "type": "WORD"}, {"start": 55.99, "end": 56.0, "text": "de", "type": "WORD"}, {"start": 56.0, "end": 56.0, "text": "diarrhée", "type": "WORD"}, {"start": 56.0, "end": 56.0, "text": "et", "type": "WORD"}, {"start": 56.0, "end": 56.01, "text": "vous", "type": "WORD"}, {"start": 56.01, "end": 56.01, "text": "avez", "type": "WORD"}, {"start": 56.01, "end": 56.01, "text": "mal", "type": "WORD"}, {"start": 56.01, "end": 56.01, "text": "en", "type": "WORD"}, {"start": 56.01, "end": 56.01, "text": "bas", "type": "WORD"}, {"start": 56.01, "end": 56.01, "text": "du", "type": "WORD"}, {"start": 56.01, "end": 56.01, "text": "ventre", "type": "WORD"}, {"start": 56.01, "end": 56.01, "text": "en", "type": "WORD"}, {"start": 56.01, "end": 56.01, "text": "haut", "type": "WORD"}, {"start": 56.01, "end": 56.01, "text": "du", "type": "WORD"}, {"start": 56.01, "end": 56.01, "text": "ventre", "type": "WORD"}, {"start": 56.01, "end": 56.01, "text": "?", "type": "PUNCTUATION"}]}, {"speaker": {"id": "patient", "name": ""}, "start": 57.57, "end": 59.42, "terms": [{"start": 57.57, "end": 57.94, "text": "hum", "type": "WORD"}, {"start": 57.94, "end": 58.31, "text": "un", "type": "WORD"}, {"start": 58.31, "end": 58.68, "text": "peu", "type": "WORD"}, {"start": 58.68, "end": 59.05, "text": "en", "type": "WORD"}, {"start": 59.05, "end": 59.239999999999995, "text": "haut", "type": "WORD"}, {"start": 59.239999999999995, "end": 59.42, "text": "heu", "type": "WORD"}]}, {"speaker": {"id": "medecin", "name": ""}, "start": 61.209999999999994, "end": 62.349999999999994, "terms": [{"start": 61.209999999999994, "end": 61.489999999999995, "text": "au", "type": "WORD"}, {"start": 61.489999999999995, "end": 61.78, "text": "niveau", "type": "WORD"}, {"start": 61.78, "end": 62.06, "text": "de", "type": "WORD"}, {"start": 62.06, "end": 62.349999999999994, "text": "l'estomac", "type": "WORD"}, {"start": 62.349999999999994, "end": 62.349999999999994, "text": "?", "type": "PUNCTUATION"}]}, {"speaker": {"id": "patient", "name": ""}, "start": 63.18000000000001, "end": 64.53, "terms": [{"start": 63.18000000000001, "end": 63.629999999999995, "text": "oui", "type": "WORD"}, {"start": 63.629999999999995, "end": 64.08, "text": "c'est", "type": "WORD"}, {"start": 64.08, "end": 64.53, "text": "ça", "type": "WORD"}]}, {"speaker": {"id": "medecin", "name": ""}, "start": 64.72, "end": 65.57, "terms": [{"start": 64.72, "end": 65.15, "text": "ça", "type": "WORD"}, {"start": 65.15, "end": 65.57, "text": "brûle", "type": "WORD"}, {"start": 65.57, "end": 65.57, "text": "?", "type": "PUNCTUATION"}]}, {"speaker": {"id": "patient", "name": ""}, "start": 67.52, "end": 70.95, "terms": [{"start": 67.52, "end": 68.21, "text": "hum", "type": "WORD"}, {"start": 68.21, "end": 68.89, "text": "je", "type": "WORD"}, {"start": 68.89, "end": 69.58, "text": "je", "type": "WORD"}, {"start": 69.58, "end": 70.26, "text": "un", "type": "WORD"}, {"start": 70.26, "end": 70.95, "text": "peu", "type": "WORD"}]}, {"speaker": {"id": "medecin", "name": ""}, "start": 71.07, "end": 74.19, "terms": [{"start": 71.07, "end": 71.27, "text": "la", "type": "WORD"}, {"start": 71.27, "end": 71.46, "text": "douleur", "type": "WORD"}, {"start": 71.46, "end": 71.66, "text": "est", "type": "WORD"}, {"start": 71.66, "end": 71.85, "text": "ce", "type": "WORD"}, {"start": 71.85, "end": 72.05, "text": "que", "type": "WORD"}, {"start": 72.05, "end": 72.24, "text": "elle", "type": "WORD"}, {"start": 72.24, "end": 72.44, "text": "a", "type": "WORD"}, {"start": 72.44, "end": 72.63, "text": "tendance", "type": "WORD"}, {"start": 72.63, "end": 72.83, "text": "à", "type": "WORD"}, {"start": 72.83, "end": 73.02, "text": "remonter", "type": "WORD"}, {"start": 73.02, "end": 73.22, "text": "ou", "type": "WORD"}, {"start": 73.22, "end": 73.41, "text": "elle", "type": "WORD"}, {"start": 73.41, "end": 73.61, "text": "reste", "type": "WORD"}, {"start": 73.61, "end": 73.8, "text": "au", "type": "WORD"}, {"start": 73.8, "end": 74.0, "text": "même", "type": "WORD"}, {"start": 74.0, "end": 74.19, "text": "endroit", "type": "WORD"}, {"start": 74.19, "end": 74.19, "text": "?", "type": "PUNCTUATION"}]}, {"speaker": {"id": "patient", "name": ""}, "start": 75.76, "end": 80.77, "terms": [{"start": 75.76, "end": 76.18, "text": "hum", "type": "WORD"}, {"start": 76.18, "end": 76.59, "text": "je", "type": "WORD"}, {"start": 76.59, "end": 77.01, "text": "sais", "type": "WORD"}, {"start": 77.01, "end": 77.43, "text": "pas", "type": "WORD"}, {"start": 77.43, "end": 77.43, "text": ".", "type": "PUNCTUATION"}, {"start": 77.43, "end": 77.85, "text": "je", "type": "WORD"}, {"start": 77.85, "end": 78.26, "text": "sais", "type": "WORD"}, {"start": 78.26, "end": 78.68, "text": "pas", "type": "WORD"}, {"start": 78.68, "end": 79.1, "text": "vous", "type": "WORD"}, {"start": 79.1, "end": 79.52, "text": "dire", "type": "WORD"}, {"start": 79.52, "end": 79.93, "text": "là", "type": "WORD"}, {"start": 79.93, "end": 80.35, "text": "comme", "type": "WORD"}, {"start": 80.35, "end": 80.77, "text": "ça", "type": "WORD"}]}, {"speaker": {"id": "medecin", "name": ""}, "start": 81.41, "end": 83.53, "terms": [{"start": 81.41, "end": 81.6, "text": "est", "type": "WORD"}, {"start": 81.6, "end": 81.79, "text": "ce", "type": "WORD"}, {"start": 81.79, "end": 81.99, "text": "que", "type": "WORD"}, {"start": 81.99, "end": 82.18, "text": "vous", "type": "WORD"}, {"start": 82.18, "end": 82.37, "text": "avez", "type": "WORD"}, {"start": 82.37, "end": 82.56, "text": "mal", "type": "WORD"}, {"start": 82.56, "end": 82.76, "text": "ailleurs", "type": "WORD"}, {"start": 82.76, "end": 82.95, "text": "que", "type": "WORD"}, {"start": 82.95, "end": 83.14, "text": "dans", "type": "WORD"}, {"start": 83.14, "end": 83.34, "text": "le", "type": "WORD"}, {"start": 83.34, "end": 83.53, "text": "ventre", "type": "WORD"}, {"start": 83.53, "end": 83.53, "text": "?", "type": "PUNCTUATION"}]}, {"speaker": {"id": "patient", "name": ""}, "start": 84.74, "end": 90.32, "terms": [{"start": 84.74, "end": 86.6, "text": "hum", "type": "WORD"}, {"start": 86.6, "end": 88.46, "text": "un", "type": "WORD"}, {"start": 88.46, "end": 88.69, "text": "peu", "type": "WORD"}, {"start": 88.69, "end": 88.92, "text": "un", "type": "WORD"}, {"start": 88.92, "end": 89.16, "text": "peu", "type": "WORD"}, {"start": 89.16, "end": 89.39, "text": "en", "type": "WORD"}, {"start": 89.39, "end": 89.62, "text": "au", "type": "WORD"}, {"start": 89.62, "end": 89.85, "text": "dos", "type": "WORD"}, {"start": 89.85, "end": 90.09, "text": "au", "type": "WORD"}, {"start": 90.09, "end": 90.17, "text": "bras", "type": "WORD"}, {"start": 90.17, "end": 90.24, "text": "un", "type": "WORD"}, {"start": 90.24, "end": 90.28, "text": "peu", "type": "WORD"}, {"start": 90.28, "end": 90.32, "text": "aussi", "type": "WORD"}]}, {"speaker": {"id": "medecin", "name": ""}, "start": 90.33, "end": 91.7, "terms": [{"start": 90.33, "end": 90.53, "text": "au", "type": "WORD"}, {"start": 90.53, "end": 90.72, "text": "bras", "type": "WORD"}, {"start": 90.72, "end": 90.92, "text": "gauche", "type": "WORD"}, {"start": 90.92, "end": 91.11, "text": "ou", "type": "WORD"}, {"start": 91.11, "end": 91.31, "text": "au", "type": "WORD"}, {"start": 91.31, "end": 91.5, "text": "bras", "type": "WORD"}, {"start": 91.5, "end": 91.7, "text": "droit", "type": "WORD"}, {"start": 91.7, "end": 91.7, "text": "?", "type": "PUNCTUATION"}]}, {"speaker": {"id": "patient", "name": ""}, "start": 92.76, "end": 96.64, "terms": [{"start": 92.76, "end": 94.71, "text": "hum", "type": "WORD"}, {"start": 94.71, "end": 95.36, "text": "pff", "type": "WORD"}, {"start": 95.36, "end": 96.01, "text": "bras", "type": "WORD"}, {"start": 96.01, "end": 96.64, "text": "gauche", "type": "WORD"}]}, {"speaker": {"id": "medecin", "name": ""}, "start": 96.64, "end": 99.04, "terms": [{"start": 96.64, "end": 97.04, "text": "vous", "type": "WORD"}, {"start": 97.04, "end": 97.44, "text": "avez", "type": "WORD"}, {"start": 97.44, "end": 97.84, "text": "mal", "type": "WORD"}, {"start": 97.84, "end": 98.24, "text": "au", "type": "WORD"}, {"start": 98.24, "end": 98.64, "text": "bras", "type": "WORD"}, {"start": 98.64, "end": 98.69, "text": "gauche", "type": "WORD"}, {"start": 98.69, "end": 98.69, "text": ".", "type": "PUNCTUATION"}, {"start": 98.69, "end": 98.74, "text": "est", "type": "WORD"}, {"start": 98.74, "end": 98.79, "text": "ce", "type": "WORD"}, {"start": 98.79, "end": 98.84, "text": "que", "type": "WORD"}, {"start": 98.84, "end": 98.89, "text": "vous", "type": "WORD"}, {"start": 98.89, "end": 98.94, "text": "avez", "type": "WORD"}, {"start": 98.94, "end": 98.99, "text": "mal", "type": "WORD"}, {"start": 98.99, "end": 99.0, "text": "dans", "type": "WORD"}, {"start": 99.0, "end": 99.02, "text": "la", "type": "WORD"}, {"start": 99.02, "end": 99.03, "text": "mâchoire", "type": "WORD"}, {"start": 99.03, "end": 99.04, "text": "aussi", "type": "WORD"}, {"start": 99.04, "end": 99.04, "text": "?", "type": "PUNCTUATION"}]}, {"speaker": {"id": "patient", "name": ""}, "start": 99.71, "end": 103.63, "terms": [{"start": 99.71, "end": 101.67, "text": "hum", "type": "WORD"}, {"start": 101.67, "end": 101.87, "text": "non", "type": "WORD"}, {"start": 101.87, "end": 102.06, "text": "mais", "type": "WORD"}, {"start": 102.06, "end": 102.26, "text": "j'ai", "type": "WORD"}, {"start": 102.26, "end": 102.45, "text": "un", "type": "WORD"}, {"start": 102.45, "end": 102.65, "text": "peu", "type": "WORD"}, {"start": 102.65, "end": 102.84, "text": "mal", "type": "WORD"}, {"start": 102.84, "end": 103.04, "text": "à", "type": "WORD"}, {"start": 103.04, "end": 103.23, "text": "la", "type": "WORD"}, {"start": 103.23, "end": 103.43, "text": "gorge", "type": "WORD"}, {"start": 103.43, "end": 103.63, "text": "aussi", "type": "WORD"}]}, {"speaker": {"id": "medecin", "name": ""}, "start": 106.13, "end": 109.84, "terms": [{"start": 106.13, "end": 106.36, "text": "vous", "type": "WORD"}, {"start": 106.36, "end": 106.59, "text": "avez", "type": "WORD"}, {"start": 106.59, "end": 106.83, "text": "mal", "type": "WORD"}, {"start": 106.83, "end": 107.06, "text": "à", "type": "WORD"}, {"start": 107.06, "end": 107.29, "text": "la", "type": "WORD"}, {"start": 107.29, "end": 107.52, "text": "gorge", "type": "WORD"}, {"start": 107.52, "end": 107.52, "text": ".", "type": "PUNCTUATION"}, {"start": 107.52, "end": 107.75, "text": "vous", "type": "WORD"}, {"start": 107.75, "end": 107.98, "text": "avez", "type": "WORD"}, {"start": 107.98, "end": 108.22, "text": "mal", "type": "WORD"}, {"start": 108.22, "end": 108.45, "text": "à", "type": "WORD"}, {"start": 108.45, "end": 108.68, "text": "la", "type": "WORD"}, {"start": 108.68, "end": 108.91, "text": "gorge", "type": "WORD"}, {"start": 108.91, "end": 109.14, "text": "depuis", "type": "WORD"}, {"start": 109.14, "end": 109.38, "text": "combien", "type": "WORD"}, {"start": 109.38, "end": 109.61, "text": "de", "type": "WORD"}, {"start": 109.61, "end": 109.84, "text": "temps", "type": "WORD"}, {"start": 109.84, "end": 109.84, "text": "?", "type": "PUNCTUATION"}]}, {"speaker": {"id": "patient", "name": ""}, "start": 111.29, "end": 112.27, "terms": [{"text": "ce", "start": 111.29, "end": 111.78, "type": "WORD"}, {"text": "matin", "start": 111.78, "end": 112.27, "type": "WORD"}]}, {"speaker": {"id": "medecin", "name": ""}, "start": 115.25, "end": 117.74, "terms": [{"start": 115.25, "end": 115.47, "text": "est", "type": "WORD"}, {"start": 115.47, "end": 115.7, "text": "ce", "type": "WORD"}, {"start": 115.7, "end": 115.93, "text": "que", "type": "WORD"}, {"start": 115.93, "end": 116.15, "text": "vous", "type": "WORD"}, {"start": 116.15, "end": 116.38, "text": "avez", "type": "WORD"}, {"start": 116.38, "end": 116.61, "text": "pris", "type": "WORD"}, {"start": 116.61, "end": 116.83, "text": "des", "type": "WORD"}, {"start": 116.83, "end": 117.06, "text": "médicaments", "type": "WORD"}, {"start": 117.06, "end": 117.28, "text": "pour", "type": "WORD"}, {"start": 117.28, "end": 117.51, "text": "vous", "type": "WORD"}, {"start": 117.51, "end": 117.74, "text": "soulager", "type": "WORD"}, {"start": 117.74, "end": 117.74, "text": "?", "type": "PUNCTUATION"}]}, {"speaker": {"id": "patient", "name": ""}, "start": 119.07, "end": 122.22, "terms": [{"start": 119.07, "end": 120.65, "text": "hum", "type": "WORD"}, {"start": 120.65, "end": 120.96, "text": "j'ai", "type": "WORD"}, {"start": 120.96, "end": 121.28, "text": "pris", "type": "WORD"}, {"start": 121.28, "end": 121.59, "text": "un", "type": "WORD"}, {"start": 121.59, "end": 121.91, "text": "do-", "type": "WORD"}, {"start": 121.91, "end": 122.07, "text": "doli-", "type": "WORD"}, {"start": 122.07, "end": 122.22, "text": "DOLIPRANE", "type": "WORD"}, {"start": 122.22, "end": 122.22, "text": "?", "type": "PUNCTUATION"}]}, {"speaker": {"id": "medecin", "name": ""}, "start": 122.27, "end": 123.22, "terms": [{"start": 122.27, "end": 122.75, "text": "un", "type": "WORD"}, {"start": 122.75, "end": 123.22, "text": "DOLIPRANE", "type": "WORD"}]}, {"speaker": {"id": "patient", "name": ""}, "start": 125.0, "end": 127.19999999999999, "terms": [{"start": 125.0, "end": 125.36000000000001, "text": "voilà", "type": "WORD"}, {"start": 125.36000000000001, "end": 125.72999999999999, "text": "ça", "type": "WORD"}, {"start": 125.72999999999999, "end": 126.1, "text": "m'a", "type": "WORD"}, {"start": 126.1, "end": 126.47, "text": "pas", "type": "WORD"}, {"start": 126.47, "end": 126.83000000000001, "text": "trop", "type": "WORD"}, {"start": 126.83000000000001, "end": 127.19999999999999, "text": "soulagée", "type": "WORD"}]}, {"speaker": {"id": "medecin", "name": ""}, "start": 129.01, "end": 130.69, "terms": [{"start": 129.01, "end": 129.22, "text": "est", "type": "WORD"}, {"start": 129.22, "end": 129.43, "text": "ce", "type": "WORD"}, {"start": 129.43, "end": 129.64, "text": "que", "type": "WORD"}, {"start": 129.64, "end": 129.85, "text": "vous", "type": "WORD"}, {"start": 129.85, "end": 130.06, "text": "avez", "type": "WORD"}, {"start": 130.06, "end": 130.27, "text": "envie", "type": "WORD"}, {"start": 130.27, "end": 130.48, "text": "de", "type": "WORD"}, {"start": 130.48, "end": 130.69, "text": "vomir", "type": "WORD"}, {"start": 130.69, "end": 130.69, "text": "?", "type": "PUNCTUATION"}]}, {"speaker": {"id": "patient", "name": ""}, "start": 131.86, "end": 134.12, "terms": [{"start": 131.86, "end": 132.99, "text": "hum", "type": "WORD"}, {"start": 132.99, "end": 134.12, "text": "oui", "type": "WORD"}]}, {"speaker": {"id": "medecin", "name": ""}, "start": 136.78, "end": 138.78, "terms": [{"start": 136.78, "end": 136.97, "text": "est", "type": "WORD"}, {"start": 136.97, "end": 137.15, "text": "ce", "type": "WORD"}, {"start": 137.15, "end": 137.33, "text": "que", "type": "WORD"}, {"start": 137.33, "end": 137.51, "text": "vous", "type": "WORD"}, {"start": 137.51, "end": 137.69, "text": "avez", "type": "WORD"}, {"start": 137.69, "end": 137.88, "text": "déjà", "type": "WORD"}, {"start": 137.88, "end": 138.06, "text": "eu", "type": "WORD"}, {"start": 138.06, "end": 138.24, "text": "ce", "type": "WORD"}, {"start": 138.24, "end": 138.42, "text": "genre", "type": "WORD"}, {"start": 138.42, "end": 138.6, "text": "de", "type": "WORD"}, {"start": 138.6, "end": 138.78, "text": "douleur", "type": "WORD"}, {"start": 138.78, "end": 138.78, "text": "?", "type": "PUNCTUATION"}]}, {"speaker": {"id": "patient", "name": ""}, "start": 140.58, "end": 142.3, "terms": [{"start": 140.58, "end": 141.28, "text": "hum", "type": "WORD"}, {"start": 141.28, "end": 141.54, "text": "non", "type": "WORD"}, {"start": 141.54, "end": 141.79, "text": "pas", "type": "WORD"}, {"start": 141.79, "end": 142.04, "text": "comme", "type": "WORD"}, {"start": 142.04, "end": 142.3, "text": "ça", "type": "WORD"}]}, {"speaker": {"id": "medecin", "name": ""}, "start": 142.98, "end": 144.3, "terms": [{"start": 142.98, "end": 143.24, "text": "ça", "type": "WORD"}, {"start": 143.24, "end": 143.51, "text": "vous", "type": "WORD"}, {"start": 143.51, "end": 143.77, "text": "est", "type": "WORD"}, {"start": 143.77, "end": 144.03, "text": "jamais", "type": "WORD"}, {"start": 144.03, "end": 144.3, "text": "arrivé", "type": "WORD"}, {"start": 144.3, "end": 144.3, "text": "?", "type": "PUNCTUATION"}]}, {"speaker": {"id": "patient", "name": ""}, "start": 145.75, "end": 146.05, "terms": [{"start": 145.75, "end": 146.05, "text": "non", "type": "WORD"}]}, {"speaker": {"id": "medecin", "name": ""}, "start": 146.36, "end": 155.15, "terms": [{"start": 146.36, "end": 148.56, "text": "donc", "type": "WORD"}, {"start": 148.56, "end": 150.76, "text": "si", "type": "WORD"}, {"start": 150.76, "end": 152.95, "text": "je", "type": "WORD"}, {"start": 152.95, "end": 153.5, "text": "résume", "type": "WORD"}, {"start": 153.5, "end": 154.05, "text": "vous", "type": "WORD"}, {"start": 154.05, "end": 154.6, "text": "avez", "type": "WORD"}, {"start": 154.6, "end": 154.68, "text": "mal", "type": "WORD"}, {"start": 154.68, "end": 154.76, "text": "en", "type": "WORD"}, {"start": 154.76, "end": 154.83, "text": "haut", "type": "WORD"}, {"start": 154.83, "end": 154.91, "text": "du", "type": "WORD"}, {"start": 154.91, "end": 154.99, "text": "ventre", "type": "WORD"}, {"start": 154.99, "end": 155.07, "text": "au", "type": "WORD"}, {"start": 155.07, "end": 155.1, "text": "niveau", "type": "WORD"}, {"start": 155.1, "end": 155.12, "text": "de", "type": "WORD"}, {"start": 155.12, "end": 155.13, "text": "l'estomac", "type": "WORD"}, {"start": 155.13, "end": 155.13, "text": "ça", "type": "WORD"}, {"start": 155.13, "end": 155.14, "text": "vous", "type": "WORD"}, {"start": 155.14, "end": 155.14, "text": "brûle", "type": "WORD"}, {"start": 155.14, "end": 155.14, "text": "vous", "type": "WORD"}, {"start": 155.14, "end": 155.14, "text": "avez", "type": "WORD"}, {"start": 155.14, "end": 155.14, "text": "aussi", "type": "WORD"}, {"start": 155.14, "end": 155.15, "text": "mal", "type": "WORD"}, {"start": 155.15, "end": 155.15, "text": "dans", "type": "WORD"}, {"start": 155.15, "end": 155.15, "text": "la", "type": "WORD"}, {"start": 155.15, "end": 155.15, "text": "gorge", "type": "WORD"}, {"start": 155.15, "end": 155.15, "text": "depuis", "type": "WORD"}, {"start": 155.15, "end": 155.15, "text": "ce", "type": "WORD"}, {"start": 155.15, "end": 155.15, "text": "m-", "type": "WORD"}, {"start": 155.15, "end": 155.15, "text": "ce", "type": "WORD"}, {"start": 155.15, "end": 155.15, "text": "matin", "type": "WORD"}, {"start": 155.15, "end": 155.15, "text": "et", "type": "WORD"}, {"start": 155.15, "end": 155.15, "text": "vous", "type": "WORD"}, {"start": 155.15, "end": 155.15, "text": "avez", "type": "WORD"}, {"start": 155.15, "end": 155.15, "text": "aussi", "type": "WORD"}, {"start": 155.15, "end": 155.15, "text": "envie", "type": "WORD"}, {"start": 155.15, "end": 155.15, "text": "de", "type": "WORD"}, {"start": 155.15, "end": 155.15, "text": "vomir", "type": "WORD"}]}, {"speaker": {"id": "patient", "name": ""}, "start": 156.76, "end": 157.44, "terms": [{"start": 156.76, "end": 157.1, "text": "c'est", "type": "WORD"}, {"start": 157.1, "end": 157.44, "text": "ça", "type": "WORD"}]}, {"speaker": {"id": "medecin", "name": ""}, "start": 157.44, "end": 159.64, "terms": [{"start": 157.44, "end": 157.64, "text": "il", "type": "WORD"}, {"start": 157.64, "end": 157.84, "text": "y", "type": "WORD"}, {"start": 157.84, "end": 158.04, "text": "a", "type": "WORD"}, {"start": 158.04, "end": 158.24, "text": "des", "type": "WORD"}, {"start": 158.24, "end": 158.44, "text": "gens", "type": "WORD"}, {"start": 158.44, "end": 158.64, "text": "qui", "type": "WORD"}, {"start": 158.64, "end": 158.84, "text": "sont", "type": "WORD"}, {"start": 158.84, "end": 159.04, "text": "​malades", "type": "WORD"}, {"start": 159.14, "end": 159.24, "text": "autour", "type": "WORD"}, {"start": 159.24, "end": 159.44, "text": "de", "type": "WORD"}, {"start": 159.44, "end": 159.64, "text": "vous", "type": "WORD"}, {"start": 159.64, "end": 159.64, "text": "?", "type": "PUNCTUATION"}]}, {"speaker": {"id": "patient", "name": ""}, "start": 160.54, "end": 162.16, "terms": [{"start": 160.54, "end": 161.35, "text": "hum", "type": "WORD"}, {"start": 161.35, "end": 162.16, "text": "non", "type": "WORD"}]}, {"speaker": {"id": "patient", "name": ""}, "start": 165.9, "end": 167.66, "terms": [{"start": 165.9, "end": 166.3, "text": "non", "type": "WORD"}, {"start": 166.3, "end": 166.7, "text": "non", "type": "WORD"}, {"start": 166.7, "end": 167.1, "text": "j'ai", "type": "WORD"}, {"start": 167.1, "end": 167.3, "text": "personne", "type": "WORD"}, {"start": 167.3, "end": 167.66, "text": "là", "type": "WORD"}]}, {"speaker": {"id": "medecin", "name": ""}, "start": 169.13, "end": 181.43, "terms": [{"start": 169.13, "end": 172.21, "text": "bon", "type": "WORD"}, {"start": 172.21, "end": 175.28, "text": "alors", "type": "WORD"}, {"start": 175.28, "end": 178.36, "text": "il", "type": "WORD"}, {"start": 178.36, "end": 178.8, "text": "faut", "type": "WORD"}, {"start": 178.8, "end": 179.24, "text": "heu", "type": "WORD"}, {"start": 179.24, "end": 179.68, "text": "on", "type": "WORD"}, {"start": 179.68, "end": 180.12, "text": "va", "type": "WORD"}, {"start": 180.12, "end": 180.55, "text": "faire", "type": "WORD"}, {"start": 180.55, "end": 180.99, "text": "passer", "type": "WORD"}, {"start": 180.99, "end": 181.21, "text": "un", "type": "WORD"}, {"start": 181.21, "end": 181.24, "text": "médecin", "type": "WORD"}, {"start": 181.24, "end": 181.27, "text": "heu", "type": "WORD"}, {"start": 181.27, "end": 181.29, "text": "à", "type": "WORD"}, {"start": 181.29, "end": 181.32, "text": "domicile", "type": "WORD"}, {"start": 181.32, "end": 181.35, "text": "madame", "type": "WORD"}, {"start": 181.35, "end": 181.38, "text": "il", "type": "WORD"}, {"start": 181.38, "end": 181.4, "text": "va", "type": "WORD"}, {"start": 181.4, "end": 181.41, "text": "arriver", "type": "WORD"}, {"start": 181.41, "end": 181.42, "text": "dans", "type": "WORD"}, {"start": 181.42, "end": 181.42, "text": "les", "type": "WORD"}, {"start": 181.42, "end": 181.42, "text": "quatre", "type": "WORD"}, {"start": 181.42, "end": 181.43, "text": "à", "type": "WORD"}, {"start": 181.43, "end": 181.43, "text": "six", "type": "WORD"}, {"start": 181.43, "end": 181.43, "text": "heures", "type": "WORD"}, {"start": 181.43, "end": 181.43, "text": "si", "type": "WORD"}, {"start": 181.43, "end": 181.43, "text": "la", "type": "WORD"}, {"start": 181.43, "end": 181.43, "text": "douleur", "type": "WORD"}, {"start": 181.43, "end": 181.43, "text": "si", "type": "WORD"}, {"start": 181.43, "end": 181.43, "text": "les", "type": "WORD"}, {"start": 181.43, "end": 181.43, "text": "symptômes", "type": "WORD"}, {"start": 181.43, "end": 181.43, "text": "s'aggravent", "type": "WORD"}, {"start": 181.43, "end": 181.43, "text": "entre", "type": "WORD"}, {"start": 181.43, "end": 181.43, "text": "temps", "type": "WORD"}, {"start": 181.43, "end": 181.43, "text": "vous", "type": "WORD"}, {"start": 181.43, "end": 181.43, "text": "rappelez", "type": "WORD"}, {"start": 181.43, "end": 181.43, "text": "le", "type": "WORD"}, {"start": 181.43, "end": 181.43, "text": "15", "type": "WORD"}]}, {"speaker": {"id": "patient", "name": ""}, "start": 181.72, "end": 185.8, "terms": [{"start": 181.72, "end": 183.76, "text": "d'accord", "type": "WORD"}, {"start": 183.76, "end": 184.1, "text": "ok", "type": "WORD"}, {"start": 184.1, "end": 184.44, "text": "un", "type": "WORD"}, {"start": 184.44, "end": 184.78, "text": "médecin", "type": "WORD"}, {"start": 184.78, "end": 185.12, "text": "à", "type": "WORD"}, {"start": 185.12, "end": 185.46, "text": "la", "type": "WORD"}, {"start": 185.46, "end": 185.63, "text": "maison", "type": "WORD"}, {"start": 185.63, "end": 185.69, "text": "super", "type": "WORD"}, {"start": 185.69, "end": 185.74, "text": "très", "type": "WORD"}, {"start": 185.74, "end": 185.8, "text": "bien", "type": "WORD"}]}, {"speaker": {"id": "medecin", "name": ""}, "start": 186.68, "end": 188.05, "terms": [{"start": 186.68, "end": 186.74, "text": "bon", "type": "WORD"}, {"start": 186.74, "end": 186.81, "text": "bah", "type": "WORD"}, {"start": 186.81, "end": 186.87, "text": "bon", "type": "WORD"}, {"start": 186.87, "end": 187.06, "text": "courage", "type": "WORD"}, {"start": 187.06, "end": 188.05, "text": "madame", "type": "WORD"}]}, {"speaker": {"id": "patient", "name": ""}, "start": 188.05, "end": 189.27, "terms": [{"start": 188.05, "end": 188.3, "text": "merci", "type": "WORD"}, {"start": 188.3, "end": 188.55, "text": "docteur", "type": "WORD"}, {"start": 188.55, "end": 188.91, "text": "au", "type": "WORD"}, {"start": 188.91, "end": 189.27, "text": "revoir", "type": "WORD"}]}]}